{"Address Book":{"Aman":[{"Zip":456325,"Address":"Dhanbad","FirstName":"Aman","State":"sdff","LastName":"Kumar","City":"df","Mobile":785496320}],"Amit":[{"Zip":123526,"Address":"sdfn","FirstName":"Amit","State":"sdf","LastName":"Kumar","City":"sdf","Mobile":4125639870}],"Anand":[{"Zip":125463,"Address":"asd","FirstName":"Anand","State":"sd","LastName":"Dandi","City":"asd","Mobile":7412589630}],"Tamil":[{"Zip":412563,"Address":"asda","FirstName":"Tamil","State":"asd","LastName":"asd","City":"asdasd","Mobile":123564789}],"Sudeep":[{"Zip":789630,"Address":"sf","FirstName":"Sudeep","State":"sferf","LastName":"sdf","City":"sf","Mobile":7485963621}]}}